{
  "id": "n1782816193917",
  "createdAt": "2026-06-30T10:43:13.917Z",
  "images": [],
  "seoDescription": "",
  "body": "<img src=\"/uploads/1782819454867-220342974.jpg\" style=\"border-radius: 8px;\"><span style=\"letter-spacing: -0.72px;\">sfdsdfsdf</span><span style=\"letter-spacing: -0.72px;\">sfdsdfsdf</span><span style=\"letter-spacing: -0.72px;\">sfdsdfsdf</span><span style=\"letter-spacing: -0.72px;\">sfdsdfsdf</span><span style=\"letter-spacing: -0.72px;\">sfdsdfsdf</span><span style=\"letter-spacing: -0.72px;\">sfdsdfsdf</span><span style=\"letter-spacing: -0.72px;\">sfdsdfsdf</span><span style=\"letter-spacing: -0.72px;\">sfdsdfsdf</span><span style=\"letter-spacing: -0.72px;\">sfdsdfsdf</span><span style=\"letter-spacing: -0.72px;\">sfdsdfsdf</span><span style=\"letter-spacing: -0.72px;\">sfdsdfsdf</span><span style=\"letter-spacing: -0.72px;\">sfdsdfsdf</span><span style=\"letter-spacing: -0.72px;\">sfdsdfsdf</span><span style=\"letter-spacing: -0.72px;\">sfdsdfsdf</span><span style=\"letter-spacing: -0.72px;\">sfdsdfsdf</span><span style=\"letter-spacing: -0.72px;\">sfdsdfsdf</span><span style=\"letter-spacing: -0.72px;\">sfdsdfsdf</span><span style=\"letter-spacing: -0.72px;\">sfdsdfsdf</span><span style=\"letter-spacing: -0.72px;\">sfdsdfsdf</span><span style=\"letter-spacing: -0.72px;\">sfdsdfsdf</span><span style=\"letter-spacing: -0.72px;\">sfdsdfsdf</span><span style=\"letter-spacing: -0.72px;\">sfdsdfsdf</span><span style=\"letter-spacing: -0.72px;\">sfdsdfsdf</span><span style=\"letter-spacing: -0.72px;\">sfdsdfsdf</span><span style=\"letter-spacing: -0.72px;\">sfdsdfsdf</span><span style=\"letter-spacing: -0.72px;\">sfdsdfsdf</span><span style=\"letter-spacing: -0.72px;\">sfdsdfsdf</span><span style=\"letter-spacing: -0.72px;\">sfdsdfsdf</span><span style=\"letter-spacing: -0.72px;\">sfdsdfsdf</span><span style=\"letter-spacing: -0.72px;\">sfdsdfsdf</span><span style=\"letter-spacing: -0.72px;\">sfdsdfsdf</span><span style=\"letter-spacing: -0.72px;\">sfdsdfsdf</span><span style=\"letter-spacing: -0.72px;\">sfdsdfsdf</span><span style=\"letter-spacing: -0.72px;\">sfdsdfsdf</span><span style=\"letter-spacing: -0.72px;\">sfdsdfsdf</span><span style=\"letter-spacing: -0.72px;\">sfdsdfsdf</span><span style=\"letter-spacing: -0.72px;\">sfdsdfsdf</span><span style=\"letter-spacing: -0.72px;\">sfdsdfsdf</span><span style=\"letter-spacing: -0.72px;\">sfdsdfsdf</span><span style=\"letter-spacing: -0.72px;\">sfdsdfsdf</span><span style=\"letter-spacing: -0.72px;\">sfdsdfsdf</span><span style=\"letter-spacing: -0.72px;\">sfdsdfsdf</span><span style=\"letter-spacing: -0.72px;\">sfdsdfsdf</span><span style=\"letter-spacing: -0.72px;\">sfdsdfsdf</span><span style=\"letter-spacing: -0.72px;\">sfdsdfsdf</span><span style=\"letter-spacing: -0.72px;\">sfdsdfsdf</span><span style=\"letter-spacing: -0.72px;\">sfdsdfsdf</span><span style=\"letter-spacing: -0.72px;\">sfdsdfsdf</span>",
  "seoTitle": "",
  "title": "sfdsdfsdfsfdsdfsdfsfdsdfsdf",
  "ogImage": "",
  "order": 2,
  "status": "published",
  "updatedAt": "2026-06-30T12:50:15.563Z"
}